odoo/addons/test_ssi_status_check_mixin/README.rst
odoo/addons/test_ssi_status_check_mixin/__init__.py
odoo/addons/test_ssi_status_check_mixin/__manifest__.py
odoo/addons/test_ssi_status_check_mixin/models/__init__.py
odoo/addons/test_ssi_status_check_mixin/models/test_status_check.py
odoo/addons/test_ssi_status_check_mixin/security/ir.model.access.csv
odoo/addons/test_ssi_status_check_mixin/static/description/icon.png
odoo/addons/test_ssi_status_check_mixin/views/test_status_check_view.xml
odoo14_addon_test_ssi_status_check_mixin-14.0.1.2.0.dist-info/METADATA
odoo14_addon_test_ssi_status_check_mixin-14.0.1.2.0.dist-info/WHEEL
odoo14_addon_test_ssi_status_check_mixin-14.0.1.2.0.dist-info/top_level.txt
odoo14_addon_test_ssi_status_check_mixin-14.0.1.2.0.dist-info/RECORD
